Metadata-Version: 2.1
Name: vsco-downloader
Version: 0.1.5
Summary: VSCO download manager on pure REST
Home-page: https://github.com/benhacka/vsco-downloader
Author: anon
Author-email: anon@fake-mail.foobar
License: UNKNOWN
Download-URL: https://github.com/benhacka/vsco-downloader/archive/refs/tags/v.0.1.5.tar.gz
Keywords: vsco,download,scrape,parse,photo,social-network
Platform: UNKNOWN
Classifier: Programming Language :: Python :: 3
Classifier: Programming Language :: Python :: 3.7
Classifier: Programming Language :: Python :: 3.8
Classifier: Programming Language :: Python :: 3.9
Requires-Python: >=3.7
License-File: LICENSE
